LICENSE.txt
MANIFEST.in
README.md
setup.cfg
setup.py
bin/qg_cli
bin/qg_cli.bat
quantgo_api/__init__.py
quantgo_api/cli.py
quantgo_api/qgapi.py
quantgo_api/qgservice.py
quantgo_api/qgutils.py
quantgo_api.egg-info/PKG-INFO
quantgo_api.egg-info/SOURCES.txt
quantgo_api.egg-info/dependency_links.txt
quantgo_api.egg-info/requires.txt
quantgo_api.egg-info/top_level.txt