Metadata-Version: 1.1
Name: quantgo-api
Version: 1.0.16
Summary: QuantGo Python API and Command Line Tool.
Home-page: https://quantgo.com
Author: Yuri Poliukhovich
Author-email: yuri@quantgo.com
License: Copyright (c) 2017 QuantGo
